MANIFEST.in
setup.py
Products/__init__.py
Products.PloneHotfix20131210.egg-info/PKG-INFO
Products.PloneHotfix20131210.egg-info/SOURCES.txt
Products.PloneHotfix20131210.egg-info/dependency_links.txt
Products.PloneHotfix20131210.egg-info/entry_points.txt
Products.PloneHotfix20131210.egg-info/namespace_packages.txt
Products.PloneHotfix20131210.egg-info/not-zip-safe
Products.PloneHotfix20131210.egg-info/requires.txt
Products.PloneHotfix20131210.egg-info/top_level.txt
Products/PloneHotfix20131210/README.txt
Products/PloneHotfix20131210/__init__.py
Products/PloneHotfix20131210/browser_id_manager.py
Products/PloneHotfix20131210/catalog.py
Products/PloneHotfix20131210/factory.py
Products/PloneHotfix20131210/image.py
docs/HISTORY.txt
docs/INSTALL.txt
docs/LICENSE.GPL
docs/LICENSE.txt