Metadata-Version: 1.1
Name: Products.PloneHotfix20131210
Version: 1.0
Summary: Various Plone hotfixes, 2013-12-10
Home-page: http://github.com/plone
Author: Plone Security Team
Author-email: security@plone.org
License: GPL
Keywords: plone security hotfix patch
Platform: UNKNOWN
Classifier: Framework :: Plone
Classifier: Programming Language :: Python
